src/__init__.py
colpyt-0.0.6.dist-info/METADATA
colpyt-0.0.6.dist-info/WHEEL
colpyt-0.0.6.dist-info/licenses/LICENSE
colpyt-0.0.6.dist-info/RECORD
