Metadata-Version: 2.1
Name: colpyt
Version: 0.0.6
Summary: Code With C O L O R S
Project-URL: Homepage, https://github.com/Spelis123/colpyt
Project-URL: Bug Tracker, https://github.com/Spelis123/colpyt/issues
Author-email: Spelis123 <Spelis@duck.com>
License-File: LICENSE
Classifier: License :: OSI Approved :: MIT License
Classifier: Operating System :: OS Independent
Classifier: Programming Language :: Python :: 3
Requires-Python: >=3.7
